spatialite/__init__.py
spatialite/connection.py
spatialite/version.py
spatialite-0.0.3.dist-info/LICENSE
spatialite-0.0.3.dist-info/METADATA
spatialite-0.0.3.dist-info/WHEEL
spatialite-0.0.3.dist-info/top_level.txt
spatialite-0.0.3.dist-info/RECORD
