Metadata-Version: 1.1
Name: spatialite
Version: 0.0.3
Summary: Wrapper of sqlite3 module which adds SpatiaLite support.
Home-page: https://github.com/malexer/spatialite
Author: Alex (Oleksii) Markov
Author-email: alex@markovs.me
License: MIT
Keywords: sqlite sqlite3 spatialite
Platform: UNKNOWN
Classifier: Development Status :: 3 - Alpha
Classifier: Intended Audience :: Developers
Classifier: License :: OSI Approved :: MIT License
Classifier: Programming Language :: Python
Classifier: Programming Language :: Python :: 2
Classifier: Programming Language :: Python :: 3
Classifier: Topic :: Database :: Database Engines/Servers
Classifier: Topic :: Software Development :: Libraries :: Python Modules
